{
    "treatment": {
        "day_1": {
            "Плавикс": {
                "frequency": 1,
                "route": "внутрь",
                "dosage": "300.0 мг",
                "total": "300.0 мг"
            },
            "Арикстра": {
                "route": "п/к",
                "total": "0.5 мл",
                "concentration": "5 МГ/мл"
            },
            "Натрия хлорид": {
                "frequency": 4,
                "route": "промыв катетера",
                "dosage": "25.0 мл",
                "total": "100.0 мл"
            },
            "Липримар": {
                "frequency": 1,
                "route": "внутрь",
                "dosage": "40.0 мг",
                "total": "40.0 мг"
            },
            "Лизиноприл": {
                "frequency": 1,
                "route": "внутрь",
                "dosage": "10.0 мг",
                "total": "10.0 мг"
            },
            "Ацекардол": {
                "frequency": 1,
                "route": "внутрь",
                "dosage": "100.0 мг",
                "total": "100.0 мг"
            },
            "Калия хлорида , Натрия хлорид": {
                "frequency": 0,
                "route": "в/в",
                "dosage": "50.0 мл",
                "total": "1.0 мл"
            }
        }
    }
}