{
    "treatment": {
        "day_1": {
            "Изокет , Натрия хлорид": {
                "frequency": 3,
                "route": "в/в",
                "dosage": "10.0 мл",
                "total": "30.0 мл"
            },
            "Лизиноприл": {
                "frequency": 1,
                "route": "внутрь",
                "dosage": "5.0 мг",
                "total": "5.0 мг"
            },
            "Натрия хлорид": {
                "frequency": 6,
                "route": "промыв катетера",
                "dosage": "25.0 мл",
                "total": "150.0 мл"
            },
            "Клексан": {
                "frequency": 1,
                "route": "п/к",
                "dosage": "0.8 мл",
                "total": "0.8 мл"
            },
            "Торвакард": {
                "frequency": 1,
                "route": "внутрь",
                "dosage": "80.0 мг",
                "total": "80.0 мг"
            }
        },
        "day_2": {
            "Лизиноприл": {
                "frequency": 1,
                "route": "внутрь",
                "dosage": "5.0 мг",
                "total": "5.0 мг"
            },
            "Натрия хлорид": {
                "frequency": 8,
                "route": "промыв катетера",
                "dosage": "25.0 мл",
                "total": "200.0 мл"
            },
            "Клексан": {
                "frequency": 2,
                "route": "п/к",
                "dosage": "0.8 мл",
                "total": "1.6 мл"
            },
            "Торвакард": {
                "frequency": 1,
                "route": "внутрь",
                "dosage": "80.0 мг",
                "total": "80.0 мг"
            },
            "Коплавикс": {
                "frequency": 1,
                "route": "внутрь",
                "dosage": "100.0 мг",
                "total": "75.0 мг"
            },
            "Кордарон": {
                "frequency": 3,
                "route": "внутрь",
                "dosage": "200.0 мг",
                "total": "600.0 мг"
            }
        },
        "day_3": {
            "Лизиноприл": {
                "frequency": 1,
                "route": "внутрь",
                "dosage": "5.0 мг",
                "total": "5.0 мг"
            },
            "Натрия хлорид": {
                "frequency": 8,
                "route": "промыв катетера",
                "dosage": "25.0 мл",
                "total": "200.0 мл"
            },
            "Клексан": {
                "frequency": 2,
                "route": "п/к",
                "dosage": "0.8 мл",
                "total": "1.6 мл"
            },
            "Торвакард": {
                "frequency": 1,
                "route": "внутрь",
                "dosage": "80.0 мг",
                "total": "80.0 мг"
            },
            "Коплавикс": {
                "frequency": 1,
                "route": "внутрь",
                "dosage": "100.0 мг",
                "total": "75.0 мг"
            },
            "Кордарон": {
                "frequency": 1,
                "route": "внутрь",
                "dosage": "200.0 мг",
                "total": "200.0 мг"
            },
            "Рингера-ацетат": {
                "frequency": 1,
                "route": "в/в капельно",
                "dosage": "500.0 мл",
                "total": "500.0 мл"
            }
        }
    }
}