{
  "treatment": {
    "": {
      "route": "внутрь",
      "dosage": "5 мг",
      "date_start": "08.09.2016",
      "date_end": "09.09.2016",
      "comment": "Амлодипин (1 таб. 5 мг) 2 р/д на 7 дн"
    },
    "Бисопролол - Прана": {
      "route": "внутрь",
      "dosage": "5 мг",
      "date_start": "08.09.2016",
      "date_end": "15.09.2016",
      "comment": "(1 таб. 5 мг) 1 р/д на 7 дн"
    },
    "Вальсакор": {
      "route": "внутрь",
      "dosage": "160 мг",
      "date_start": "08.09.2016",
      "date_end": "09.09.2016",
      "comment": "(1 таб. 160 мг) 1 р/д на 7 дн"
    },
    "Липримар": {
      "route": "внутрь",
      "dosage": "40 мг",
      "date_start": "08.09.2016",
      "date_end": "15.09.2016",
      "comment": "(1 таб. 40 мг) 1 р/д на 7 дн"
    },
    "Ацекардол": {
      "route": "внутрь",
      "dosage": "100 мг",
      "date_start": "09.09.2016",
      "date_end": "16.09.2016",
      "comment": "(1 таб. 100 мг) 1 р/д на 7 дн"
    },
    "Индапамид": {
      "route": "внутрь",
      "dosage": "2.5 мг",
      "date_start": "12.09.2016",
      "date_end": "16.09.2016",
      "comment": "(1 таб. 2.5 мг) 1 р/д на 7 дн. Утром"
    }
  }
}