[
  {
    "route": "п/к",
    "dosage": "5 мг",
    "comment": "2,/0,5 мл 0.5 мл 1 р/д на 5 дн",
    "name": "Арикстра",
    "period": "1-3"
  },
  {
    "route": "внутрь",
    "dosage": "0.4 мг",
    "comment": "(1 таб. 0.4 мг) 1 р/д на 1 дн. однократно",
    "name": "Моксонидин",
    "period": "1-2"
  },
  {
    "route": "внутрь",
    "dosage": "20 мг",
    "comment": "(1 таб. 20 мг) 2 р/д на 15 дн. вечером после еды",
    "name": "Аторвастатин-СЗ",
    "period": "3-7"
  },
  {
    "route": "внутрь",
    "dosage": "100 мг",
    "comment": "(1 таб. 100 мг) 1 р/д на 15 дн. утром после еды",
    "name": "Ацекардол",
    "period": "3-7"
  },
  {
    "route": "внутрь",
    "dosage": "5 мг",
    "comment": "(1 таб. 5 мг) 1 р/д на 15 дн. утром после еды",
    "name": "Бисопролол",
    "period": "3-7"
  },
  {
    "route": "внутрь",
    "dosage": "10 мг",
    "comment": "(1 таб. 10 мг) 1 р/д на 15 дн. вечером после еды",
    "name": "Лизиноприл",
    "period": "3-7"
  },
  {
    "route": "внутрь",
    "dosage": "20 мг",
    "comment": "1 р/д на 30 дн. Утром до еды",
    "name": "Омепразол",
    "period": "3-7"
  },
  {
    "route": "внутрь",
    "dosage": "75 мг",
    "comment": "(1 таб. 75 мг) 1 р/д на 15 дн. утром после еды",
    "name": "Плавикс",
    "period": "3-7"
  },
  {
    "route": "внутрь",
    "dosage": "100 мг",
    "comment": "(1 таб. 100 мг) 6 р/д на 10 дн. 2т*3р/день сублингвально",
    "name": "Глицин-Био Фармаплант",
    "period": "6-7"
  }
]