[
  {
    "route": "внутрь",
    "dosage": "20 мг",
    "comment": "(1 таб. 20 мг) 1 р/д на 20 дн. вечером",
    "name": "Аторвастатин",
    "period": "1-7"
  },
  {
    "route": "внутрь",
    "dosage": "100 мг",
    "comment": "(1 таб. 100 мг) 1 р/д на 20 дн. утром",
    "name": "Ацекардол",
    "period": "1-7"
  },
  {
    "route": "внутрь",
    "dosage": "5 мг",
    "comment": "(1 таб. 5 мг) 2 р/д на 20 дн. утро, вечер",
    "name": "Эликвис",
    "period": "1-7"
  },
  {
    "route": "внутрь",
    "dosage": "5 мг",
    "comment": "(1 таб. 5 мг) 1 р/д на 20 дн. утром",
    "name": "Бисопролол",
    "period": "1-7"
  },
  {
    "route": "внутрь",
    "dosage": "75 мг",
    "comment": "(1 таб. 75 мг) 1 р/д на 20 дн. вечером",
    "name": "Зилт",
    "period": "1-7"
  },
  {
    "route": "внутрь",
    "dosage": "20 мг",
    "comment": "1 р/д на 30 дн. Утром до еды",
    "name": "Омепразол",
    "period": "1-7"
  },
  {
    "route": "внутрь",
    "dosage": "25 мг",
    "comment": "(1 таб. 25 мг) 2 р/д на 20 дн. утро, обед",
    "name": "Спиронолактон",
    "period": "1-7"
  },
  {
    "route": "внутрь",
    "dosage": "100 мг",
    "comment": "(1 таб. 100 мг) 6 р/д на 10 дн. 2т*3р/день сублингвально",
    "name": "Глицин-Био Фармаплант",
    "period": "2-7"
  },
  {
    "route": "внутрь",
    "dosage": "0.25 мг",
    "comment": "(1 таб. 0.25 мг) 1 р/д на 5 дн. 1/2 таб утром",
    "name": "Дигоксин",
    "period": "6-7"
  }
]