[
  {
    "frequency": 1,
    "route": "внутрь",
    "dosage": "100.0 мг",
    "total": "100.0 мг",
    "name": "Ацекардол",
    "period": "1-2"
  },
  {
    "frequency": 1,
    "route": "внутрь",
    "dosage": "20.0 мг",
    "total": "20.0 мг",
    "name": "Лизиноприл",
    "period": "1-1"
  },
  {
    "frequency": 2,
    "route": "внутрь",
    "dosage": "300.0 мг",
    "total": "600.0 мг",
    "name": "Плавикс",
    "period": "1-1"
  },
  {
    "frequency": 0,
    "route": "в/в капельно",
    "dosage": "20.0 мл",
    "total": "2.0 мл",
    "name": "Изокет",
    "period": "1-1"
  },
  {
    "frequency": 0,
    "route": "в/в капельно",
    "dosage": "20.0 мл",
    "total": "2.0 мл",
    "name": "Натрия хлорид",
    "period": "1-1"
  },
  {
    "frequency": 4,
    "route": "промыв катетера",
    "dosage": "50.0 мл",
    "total": "200.0 мл",
    "name": "Натрия хлорид",
    "period": "1-2"
  },
  {
    "frequency": 2,
    "route": "внутрь",
    "dosage": "40.0 мг",
    "total": "80.0 мг",
    "name": "Аторвастатин",
    "period": "1-1"
  },
  {
    "frequency": 0,
    "route": "п/к",
    "dosage": "6.0 мл",
    "total": "1.2 мл",
    "name": "Эноксапарин натрия нти-Ха",
    "period": "1-2"
  },
  {
    "route": "в/в",
    "total": "10.0 мл",
    "concentration": "2 МГ/мл",
    "name": "Интегрилин",
    "period": "1-1"
  },
  {
    "frequency": 1,
    "route": "внутрь",
    "dosage": "10.0 мг",
    "total": "10.0 мг",
    "name": "Торасемид",
    "period": "1-2"
  },
  {
    "frequency": 1,
    "route": "в/в",
    "dosage": "2.0 мл",
    "total": "2.0 мл",
    "name": "Фуросемид",
    "period": "1-1"
  },
  {
    "frequency": 1,
    "route": "в/в капельно",
    "dosage": "40.0 мг",
    "total": "40.0 мг",
    "name": "Омез для инфузий",
    "period": "1-1"
  },
  {
    "frequency": 2,
    "route": "внутрь",
    "dosage": "20.0 мг",
    "total": "40.0 мг",
    "name": "Лизиноприл",
    "period": "2-2"
  },
  {
    "frequency": 1,
    "route": "внутрь",
    "dosage": "40.0 мг",
    "total": "40.0 мг",
    "name": "Аторвастатин",
    "period": "2-2"
  },
  {
    "frequency": 1,
    "route": "внутрь",
    "dosage": "75.0 мг",
    "total": "75.0 мг",
    "name": "Плавикс",
    "period": "2-2"
  },
  {
    "frequency": 2,
    "route": "внутрь",
    "dosage": "20.0 мг",
    "total": "40.0 мг",
    "name": "Эманера",
    "period": "2-2"
  }
]