[
  {
    "route": "не указан",
    "total": "3.0 мл",
    "concentration": "40 МГ/мл",
    "name": "Калия хлорид",
    "period": "1-1"
  },
  {
    "frequency": 1,
    "route": "нет",
    "dosage": "40.0 мг",
    "total": "40.0 мг",
    "name": "Аторис",
    "period": "1-5"
  },
  {
    "frequency": 0,
    "route": "нет",
    "dosage": "5.0 мг",
    "total": "2.5 мг",
    "name": "Бисопролол",
    "period": "1-1"
  },
  {
    "frequency": 1,
    "route": "нет",
    "dosage": "5.0 мг",
    "total": "5.0 мг",
    "name": "Торасемид-СЗ",
    "period": "1-1"
  },
  {
    "route": "не указан",
    "total": "5.0 мл",
    "concentration": "2 МГ/мл",
    "name": "Норадреналин Агетан",
    "period": "1-3"
  },
  {
    "route": "не указан",
    "total": "4.0 мл",
    "concentration": "2 МГ/мл",
    "name": "Норэпинефрин",
    "period": "1-2"
  },
  {
    "frequency": 4,
    "route": "нет",
    "dosage": "2.0 мл",
    "total": "7.0 мл",
    "name": "Дексмедетомидин",
    "period": "2-2"
  },
  {
    "frequency": 0,
    "route": "нет",
    "dosage": "500.0 мл",
    "total": "50.0 мл",
    "name": "Стерофундин изотонический",
    "period": "2-2"
  },
  {
    "frequency": 1,
    "route": "нет",
    "dosage": "20.0 мг",
    "total": "20.0 мг",
    "name": "Омез",
    "period": "2-10"
  },
  {
    "frequency": 0,
    "route": "нет",
    "dosage": "40.0 мг",
    "total": "20.0 мг",
    "name": "Фуросемид",
    "period": "2-2"
  },
  {
    "route": "не указан",
    "total": "4.5 мл",
    "concentration": "5 МГ/мл",
    "name": "Симдакс",
    "period": "2-4"
  },
  {
    "frequency": 1,
    "route": "нет",
    "dosage": "75.0 мг",
    "total": "75.0 мг",
    "name": "Плавикс",
    "period": "2-9"
  },
  {
    "frequency": 1,
    "route": "нет",
    "dosage": "100.0 мг",
    "total": "100.0 мг",
    "name": "Тромбо АСС",
    "period": "2-8"
  },
  {
    "frequency": 2,
    "route": "нет",
    "dosage": "2.0 мл",
    "total": "5.0 мл",
    "name": "Фуросемид",
    "period": "3-3"
  },
  {
    "frequency": 2,
    "route": "нет",
    "dosage": "2.0 мл",
    "total": "5.0 мл",
    "name": "Фуросемид",
    "period": "7-8"
  },
  {
    "route": "не указан",
    "total": "5.0 мл",
    "concentration": "40 МГ/мл",
    "name": "Калия хлорид",
    "period": "3-4"
  },
  {
    "route": "не указан",
    "total": "5.0 мл",
    "concentration": "40 МГ/мл",
    "name": "Калия хлорид",
    "period": "7-7"
  },
  {
    "route": "не указан",
    "total": "5.0 мл",
    "concentration": "40 МГ/мл",
    "name": "Калия хлорид",
    "period": "10-10"
  },
  {
    "route": "не указан",
    "total": "2.0 мл",
    "concentration": "2 МГ/мл",
    "name": "Норэпинефрин",
    "period": "3-3"
  },
  {
    "frequency": 1,
    "route": "нет",
    "dosage": "400.0 мг",
    "total": "400.0 мг",
    "name": "Мофлаксия",
    "period": "4-9"
  },
  {
    "route": "не указан",
    "total": "6.0 мл",
    "concentration": "2 МГ/мл",
    "name": "Норадреналин Агетан",
    "period": "4-4"
  },
  {
    "route": "не указан",
    "total": "10.0 мл",
    "concentration": "2 МГ/мл",
    "name": "Норадреналин",
    "period": "4-5"
  },
  {
    "frequency": 1,
    "route": "нет",
    "dosage": "5.0 мл",
    "total": "5.0 мл",
    "name": "Гепарин-натрий Браун .",
    "period": "4-4"
  },
  {
    "route": "не указан",
    "total": "1.0 мл",
    "concentration": "100 МЕ/мл",
    "name": "Протафан НМ Пенфилл",
    "period": "4-5"
  },
  {
    "frequency": 0,
    "route": "нет",
    "dosage": "5.0 мл",
    "total": "2.0 мл",
    "name": "Гепарин-натрий Браун .",
    "period": "5-5"
  },
  {
    "route": "не указан",
    "total": "8.0 мл",
    "concentration": "2 МГ/мл",
    "name": "Норадреналин Агетан",
    "period": "5-5"
  },
  {
    "route": "не указан",
    "total": "2.0 мл",
    "concentration": "50 МГ/мл",
    "name": "Амиодарон",
    "period": "5-5"
  },
  {
    "route": "не указан",
    "total": "14.0 мл",
    "concentration": "2 МГ/мл",
    "name": "Норадреналин Агетан",
    "period": "6-6"
  },
  {
    "route": "не указан",
    "total": "5.0 мл",
    "concentration": "50 МГ/мл",
    "name": "Амиодарон",
    "period": "6-10"
  },
  {
    "route": "не указан",
    "total": "10.0 мл",
    "concentration": "40 МГ/мл",
    "name": "Калия хлорид",
    "period": "9-9"
  },
  {
    "frequency": 0,
    "route": "нет",
    "dosage": "200.0 мл",
    "total": "100.0 мл",
    "name": "Натрия гидрокарбонат",
    "period": "10-10"
  }
]