{
    "day_1": {
        "Натрия хлорид 0.9% 25 мл промыв катетера": "100мл",
        "Омепразол 20 мг внутрь": "20мг",
        "Липримар 40 мг внутрь": "40мг",
        "Коплавикс 100 мг + 75 мг внутрь": "75мг",
        "Лизиноприл 10 мг внутрь": "10мг",
        "Калия хлорида 4% 30 мл, Глюкоза 5% 30 мл в/в": "1дозсмеси"
    },
    "day_2": {
        "Натрия хлорид 0.9% 25 мл промыв катетера": "100мл",
        "Омепразол 20 мг внутрь": "40мг",
        "Липримар 40 мг внутрь": "40мг",
        "Коплавикс 100 мг + 75 мг внутрь": "75мг",
        "Лизиноприл 10 мг внутрь": "20мг",
        "Клексан 8000 МЕ/ 0.8 мл п/к": "1.6мл",
        "Калия хлорида 4% 30 мл, Натрия хлорид 0.9% 30 мл в/в капельно": "2дозсмеси"
    }
}