{
    "day_1": {
        "Коплавикс 100 мг + 75 мг внутрь": "75мг",
        "Эгилок С 25 мг внутрь": "25мг",
        "Натрия хлорид 0.9% 25 мл промыв катетера": "100мл",
        "Клексан 8000 МЕ/ 0.8 мл п/к": "0.8мл",
        "Натрия хлорид 0.9% 10 мл, Изакардин 0.1% 10 мл в/в": "0(+)0",
        "Лизинотон 20 мг внутрь": "5мг",
        "Торвакард 40 мг внутрь": "40мг",
        "Калия хлорид 7.5% 50 мл, Глюкоза 5% 250 мл в/в": "1(+)0"
    },
    "day_2": {
        "Коплавикс 100 мг + 75 мг внутрь": "75мг",
        "Эгилок С 25 мг внутрь": "25мг",
        "Натрия хлорид 0.9% 25 мл промыв катетера": "100мл",
        "Клексан 8000 МЕ/ 0.8 мл п/к": "1.6мл",
        "Лизинотон 20 мг внутрь": "5мг",
        "Торвакард 40 мг внутрь": "40мг"
    }
}