{
    "day_1": {
        "Омепразол 20 мг внутрь": "20мг",
        "Ацекардол 100 мг внутрь": "100мг",
        "Клексан 4000 МЕ/ 0.4 мл п/к": "1.4мл",
        "Лизиноприл 5 мг внутрь": "5мг",
        "Аторвастатин 40 мг внутрь": "40мг",
        "Брилинта 90 мг внутрь": "180мг",
        "Бисопролол - Прана 5 мг внутрь": "5мг",
        "Калия хлорида 4% 30 мл, Натрия хлорид 0.9% 30 мл в/в капельно": "4дозсмеси"
    },
    "day_2": {
        "Ацекардол 100 мг внутрь": "100мг",
        "Лизиноприл 5 мг внутрь": "5мг",
        "Аторвастатин 40 мг внутрь": "40мг",
        "Брилинта 90 мг внутрь": "180мг",
        "Бисопролол - Прана 5 мг внутрь": "5мг",
        "Эниксум 10 000 МЕ/мл 0.6 мл п/к": "1.2мл"
    }
}