{
    "day_1": {
        "Эгилок С 25 мг внутрь": "25мг",
        "Ацекардол 100 мг внутрь": "100мг",
        "Омепразол 20 мг внутрь": "20мг",
        "Натрия хлорид 0.9% 10 мл, Изакардин 0.1% 10 мл в/в": "3(+)0",
        "Натрия хлорид 0.9% 25 мл промыв катетера": "50мл",
        "Эниксум 10 000 МЕ/мл 0.8 мл п/к": "0.8мл",
        "Аторвастатин 40 мг внутрь": "40мг",
        "Верошпилактон 25 мг внутрь": "75мг",
        "Фуросемид 1% 10 мл, Натрия хлорид 0.9% 40 мл в/в капельно": "1(+)0",
        "Вальсакор 160 мг внутрь": "40мг"
    },
    "day_2": {
        "Эгилок С 25 мг внутрь": "25мг",
        "Ацекардол 100 мг внутрь": "100мг",
        "Омепразол 20 мг внутрь": "20мг",
        "Натрия хлорид 0.9% 10 мл, Изакардин 0.1% 10 мл в/в": "3(+)0",
        "Натрия хлорид 0.9% 25 мл промыв катетера": "50мл",
        "Эниксум 10 000 МЕ/мл 0.8 мл п/к": "0.8мл",
        "Аторвастатин 40 мг внутрь": "40мг",
        "Верошпилактон 25 мг внутрь": "75мг",
        "Вальсакор 160 мг внутрь": "40мг",
        "Тригрим 10 мг внутрь": "10мг"
    }
}