{
    "day_1": {
        "Брилинта 90 мг внутрь": "270мг",
        "Лизиноприл 10 мг внутрь": "10мг",
        "Изокет 0.1% 10 мл, Натрия хлорид 0.9% 10 мл в/в капельно": "2дозсмеси",
        "Гепарин 5000ЕД/мл 0.5 мл, Натрия хлорид 0.9% 10 мл промыв катетера": "4дозсмеси",
        "Натрия хлорид 0.9% 25 мл в/в": "100мл",
        "Клексан 8000 МЕ/ 0.8 мл п/к": "0.8мл",
        "Тромбо АСС 100 мг внутрь": "100мг",
        "Аторис 40 мг внутрь": "40мг"
    },
    "day_2": {
        "Брилинта 90 мг внутрь": "180мг",
        "Лизиноприл 5 мг внутрь": "5мг",
        "Гепарин 5000ЕД/мл 0.5 мл, Натрия хлорид 0.9% 10 мл промыв катетера": "4дозсмеси",
        "Натрия хлорид 0.9% 25 мл в/в": "100мл",
        "Тромбо АСС 100 мг внутрь": "100мг",
        "Аторис 40 мг внутрь": "40мг",
        "Эгилок 25 мг внутрь": "25мг",
        "Эниксум 10 000 МЕ/мл 0.6 мл п/к": "0.4мл"
    }
}