{
    "day_1": {
        "Брилинта 90 мг внутрь": "180мг",
        "Натрия хлорид 0.9% 50 мл промыв катетера": "200мл",
        "Гепарин 5000 ЕД/мл 0.4 мл, Натрия хлорид 0.9% 50 мл промыв катетера": "4дозсмеси",
        "Аторвастатин 10 мг внутрь": "40мг",
        "Кетопрофен 50 мг/мл 2 мл парентерально": "8мл"
    },
    "day_2": {
        "Брилинта 90 мг внутрь": "180мг",
        "Натрия хлорид 0.9% 50 мл промыв катетера": "200мл",
        "Гепарин 5000 ЕД/мл 0.4 мл, Натрия хлорид 0.9% 50 мл промыв катетера": "4дозсмеси",
        "Аторвастатин 10 мг внутрь": "40мг",
        "Глюкоза 5% 30 мл, Калия хлорид 40 мг/мл 30 мл в/в": "3дозсмеси"
    },
    "day_3": {
        "Брилинта 90 мг внутрь": "180мг",
        "Натрия хлорид 0.9% 50 мл промыв катетера": "200мл",
        "Гепарин 5000 ЕД/мл 0.4 мл, Натрия хлорид 0.9% 50 мл промыв катетера": "4дозсмеси",
        "Аторвастатин 10 мг внутрь": "40мг",
        "Глюкоза 5% 30 мл, Калия хлорид 40 мг/мл 30 мл в/в": "3дозсмеси",
        "Амиодарон 50 мг/мл 12 мл, Глюкоза 5% 38 мл в/в": "3дозсмеси"
    }
}